{
  "emulator": false,
  "portName": "/dev/ttyO2",
  "packetParserBufferSize": 1024,
  "win32": {
    "portName": "COM7"
  },
  "baudrate": 115200,
  "radarSpeedTimeOutMinutes":30,
  "radarConfig": {
    "TargetDirection": {
      "id": 2,
      "value": null,
      "def": 1,
      "datatype": "int",
      "notes":"0 Outbound, 1 InBound, 2 Both"
    }, 
    "Range": {
      "id": 4,
      "value": null,
      "def": 7,
      "datatype": "int",
      "notes":"0(min) - 7(max)"
    }, 
    "LowSpeedThreshold": {
      "id": 7,
      "value": null,
      "def": 50,
      "datatype": "int",
      "notes":"0 - 900 MPH"
    }, 
    "HighSpeedThreshold": {
      "id": 11,
      "value": null,
      "def": 150,
      "datatype": "int",
      "notes":"0 - 900 MPH"
    }, 
    "AlarmApeedThreshold": {
      "id": 12,
      "value": null,
      "def": 1500,
      "datatype": "int",
      "notes":"0 - 1500 MPH Aux Pin Function"
    }, 
    "PeakSpeedEnable": {
      "id": 13,
      "value": null,
      "def": 1,
      "datatype": "int",
      "notes":"0 Disabled, 1 Enabled"
    }, 
    "AuxPinConfiguration": {
      "id": 16,
      "value": null,
      "def": 1,
      "datatype": "int",
      "notes":"0 = Radar Trigger, 1 = Off, 2 = SpeedAlarm, 3 = Doppler without Squeulch, 4 = Doopler with Sqeulch"
    }, 
    "CosignAngle1": {
      "id": 18,
      "value": null,
      "def": 0,
      "datatype": "int",
      "notes":"0-45 one degree increments"
    }, 
    "CosignAngle2": {
      "id": 19,
      "value": null,
      "def": 0,
      "datatype": "int",
      "notes":"0-45 one degree increments"
    }, 
    "Units": {
      "id": 20,
      "value": null,
      "def": 0,
      "datatype": "int",
      "notes":"0 MPH, 1 km/h, 2 knots, 3 feet/sec, 4 meters/sec"
    }, 
    "UnitResolution": {
      "id": 21,
      "value": null,
      "def": 0,
      "datatype": "int",
      "notes":"0 Ones, 1 Tenths"
    }, 
    "LeadingZeroCharacter": {
      "id": 23,
      "value": null,
      "def": 1,
      "datatype": "int",
      "notes":"0 Zero, 1 Space, 2 None"
    }, 
    "SerialPortBaudRate": {
      "id": 29,
      "value": null,
      "def": null,
      "readOnly": true,
      "datatype": "string",
      "notes":"0 300, 1 600, 2 1200, 3 2400, 4 4800, 5 9600, 6 19200, 7 38400, 8 57600, 9 115200"
    }, 
    "MessageFormat": {
      "id": 30,
      "value": null,
      "def": 3,
      "readOnly": true,
      "datatype": "int",
      "notes":"0 None, 1 A, 2 b, 3 bE, 4 S, 5 EE, 6 A1, 7 COL"
    }, 
    "MessagePeriod": {
      "id": 31,
      "value": null,
      "def": 250,
      "datatype": "int",
      "notes":"0 - 10000  10Sec delay"
    }, 
    "ProductID": {
      "id": 37,
      "value": null,
      "def": null,
      "readOnly": true,
      "datatype": "string",
      "notes":"Read Only Product ID In Ascii"
    }, 
    "TransmiterControl": {
      "id": 42,
      "value": null,
      "def": 1,
      "datatype": "int",
      "notes":"0 = Hold, 1 = Transmit"
    }, 
    "LiveTargetLock": {
      "id": 43,
      "value": null,
      "def": 0,
      "datatype": "int",
      "notes":"0 = Release, 1 = Lock"
    }, 
    "ForkMode": {
      "id": 47,
      "value": null,
      "def": 0,
      "datatype": "int",
      "notes":"0 Off, 1 On"
    }, 
    "RadarTriggerMode": {
      "id": 60,
      "value": null,
      "def": 2,
      "datatype": "int",
      "notes":"Aux Pin Function 0 Continuous, 1 Start - Stop, 2 Lock"
    }, 
    "ProductType": {
      "id": 79,
      "value": null,
      "def": null,
      "readOnly": true,
      "datatype": "hex",
      "notes":"3 Byte Code for Model"
    }, 
    "SoftwareVersion": {
      "id": 81,
      "value": null,
      "def": null,
      "readOnly": true,
      "datatype": "string",
      "notes":"Ascii String for Software Version"
    }, 
    "AutoClearDelay": {
      "id": 88,
      "value": null,
      "def": 2,
      "datatype": "int",
      "notes":"0 -10 sec, 11 20 sec, 12 30 sec, 13 Off"
    }, 
    "MessageTermination": {
      "id": 101,
      "value": null,
      "def": 0,
      "readOnly": true,
      "datatype": "int",
      "notes":"0 CR, 1 CRLF, 2 Unit CR, 3 Unit CRLF"
    }, 
    "PeakMessageType": {
      "id": 102,
      "value": null,
      "def": 0,
      "datatype": "int",
      "notes":"0 Continuous, 1 Single"
    }, 
    "TargetType": {
      "id": 103,
      "value": null,
      "def": 0,
      "datatype": "int",
      "notes":"0 Baseball, 1 Carnival, 2 Car, 3 Tennis"
    }, 
    "FormatASpeed": {
      "id": 104,
      "value": null,
      "def": 1,
      "datatype": "int",
      "notes":"0 Last/Live, 1 Peak, 2 Hit"
    }, 
    "HitSpeedEnable": {
      "id": 105,
      "value": null,
      "def": 1,
      "datatype": "int",
      "notes":"0 Disabled, 1 Enabled"
    }, 
    "SpeedSensorAddress": {
      "id": 116,
      "value": null,
      "def": 2,
      "readOnly": true,
      "datatype": "int",
      "notes":"2 RS-2323 is fixed at 2, RS-485 2 - 254"
    } 
  }

}